{
  "version": "1.0",
  "app": "AVTrack Pro",
  "created_at": "2026-04-28T00:00:00.050Z",
  "chantiers": [
    {
      "id": 7,
      "nom": "Projet Flakes",
      "client": "MC CAIN",
      "adresse": "",
      "date_debut": null,
      "date_fin": null,
      "statut": "a_faire",
      "description": "Importe depuis BDC PDF",
      "created_by": 4,
      "created_at": "2026-04-22T13:36:55.308Z",
      "updated_at": "2026-04-23T13:38:45.597Z",
      "salles": [
        {
          "id": 58,
          "chantier_id": 7,
          "nom": "MEETING ROOM",
          "etage": null,
          "statut": "a_faire",
          "commentaire": null,
          "photo_url": null,
          "net_masque": "255.255.255.0",
          "net_gateway": null,
          "net_dns": null,
          "position_ordre": 0,
          "created_at": "2026-04-22T13:36:55.315Z",
          "updated_at": "2026-04-22T13:36:55.315Z",
          "produits": [
            {
              "id": 192,
              "salle_id": 58,
              "type_equipement": "Autre",
              "reference": "SCREEN'UP MF55100",
              "serial_number": null,
              "description": "MF55100",
              "sur_reseau": false,
              "ip": null,
              "masque": null,
              "gateway": null,
              "dns": null,
              "mdp": null,
              "position_ordre": 0,
              "created_by": 4,
              "updated_by": null,
              "created_at": "2026-04-22T13:36:55.337Z",
              "updated_at": "2026-04-22T13:36:55.337Z"
            },
            {
              "id": 193,
              "salle_id": 58,
              "type_equipement": "TV",
              "reference": "SAMSUNG LH65QMCEBGCXEN",
              "serial_number": null,
              "description": "LH65QMCEBGCXEN",
              "sur_reseau": false,
              "ip": null,
              "masque": null,
              "gateway": null,
              "dns": null,
              "mdp": null,
              "position_ordre": 0,
              "created_by": 4,
              "updated_by": null,
              "created_at": "2026-04-22T13:36:55.340Z",
              "updated_at": "2026-04-22T13:36:55.340Z"
            },
            {
              "id": 194,
              "salle_id": 58,
              "type_equipement": "TV",
              "reference": "Samsung Pied",
              "serial_number": null,
              "description": "Pied",
              "sur_reseau": false,
              "ip": null,
              "masque": null,
              "gateway": null,
              "dns": null,
              "mdp": null,
              "position_ordre": 0,
              "created_by": 4,
              "updated_by": null,
              "created_at": "2026-04-22T13:36:55.341Z",
              "updated_at": "2026-04-22T13:36:55.341Z"
            },
            {
              "id": 195,
              "salle_id": 58,
              "type_equipement": "TV",
              "reference": "Samsung LH55WMBWBGCXEN",
              "serial_number": null,
              "description": "LH55WMBWBGCXEN",
              "sur_reseau": false,
              "ip": null,
              "masque": null,
              "gateway": null,
              "dns": null,
              "mdp": null,
              "position_ordre": 0,
              "created_by": 4,
              "updated_by": null,
              "created_at": "2026-04-22T13:36:55.343Z",
              "updated_at": "2026-04-22T13:36:55.343Z"
            },
            {
              "id": 196,
              "salle_id": 58,
              "type_equipement": "Autre",
              "reference": "Screen'Up SCRMF3255",
              "serial_number": null,
              "description": "SCRMF3255",
              "sur_reseau": false,
              "ip": null,
              "masque": null,
              "gateway": null,
              "dns": null,
              "mdp": null,
              "position_ordre": 0,
              "created_by": 4,
              "updated_by": null,
              "created_at": "2026-04-22T13:36:55.343Z",
              "updated_at": "2026-04-22T13:36:55.343Z"
            },
            {
              "id": 197,
              "salle_id": 58,
              "type_equipement": "Autre",
              "reference": "Screen'Up SCRMF3255",
              "serial_number": null,
              "description": "SCRMF3255",
              "sur_reseau": false,
              "ip": null,
              "masque": null,
              "gateway": null,
              "dns": null,
              "mdp": null,
              "position_ordre": 0,
              "created_by": 4,
              "updated_by": null,
              "created_at": "2026-04-22T13:36:55.345Z",
              "updated_at": "2026-04-22T13:36:55.345Z"
            },
            {
              "id": 198,
              "salle_id": 58,
              "type_equipement": "Autre",
              "reference": "Screen'Up SCRMF3255",
              "serial_number": null,
              "description": "SCRMF3255",
              "sur_reseau": false,
              "ip": null,
              "masque": null,
              "gateway": null,
              "dns": null,
              "mdp": null,
              "position_ordre": 0,
              "created_by": 4,
              "updated_by": null,
              "created_at": "2026-04-22T13:36:55.346Z",
              "updated_at": "2026-04-22T13:36:55.346Z"
            },
            {
              "id": 199,
              "salle_id": 58,
              "type_equipement": "Autre",
              "reference": "Screen'Up SCRMF3255",
              "serial_number": null,
              "description": "SCRMF3255",
              "sur_reseau": false,
              "ip": null,
              "masque": null,
              "gateway": null,
              "dns": null,
              "mdp": null,
              "position_ordre": 0,
              "created_by": 4,
              "updated_by": null,
              "created_at": "2026-04-22T13:36:55.348Z",
              "updated_at": "2026-04-22T13:36:55.348Z"
            },
            {
              "id": 200,
              "salle_id": 58,
              "type_equipement": "TV",
              "reference": "SAMSUNG LH43QMCEPGCXEN",
              "serial_number": null,
              "description": "LH43QMCEPGCXEN",
              "sur_reseau": false,
              "ip": null,
              "masque": null,
              "gateway": null,
              "dns": null,
              "mdp": null,
              "position_ordre": 0,
              "created_by": 4,
              "updated_by": null,
              "created_at": "2026-04-22T13:36:55.349Z",
              "updated_at": "2026-04-22T13:36:55.349Z"
            },
            {
              "id": 201,
              "salle_id": 58,
              "type_equipement": "TV",
              "reference": "SAMSUNG LH43QMCEPGCXEN",
              "serial_number": null,
              "description": "LH43QMCEPGCXEN",
              "sur_reseau": false,
              "ip": null,
              "masque": null,
              "gateway": null,
              "dns": null,
              "mdp": null,
              "position_ordre": 0,
              "created_by": 4,
              "updated_by": null,
              "created_at": "2026-04-22T13:36:55.352Z",
              "updated_at": "2026-04-22T13:36:55.352Z"
            },
            {
              "id": 202,
              "salle_id": 58,
              "type_equipement": "TV",
              "reference": "SAMSUNG LH43QMCEPGCXEN",
              "serial_number": null,
              "description": "LH43QMCEPGCXEN",
              "sur_reseau": false,
              "ip": null,
              "masque": null,
              "gateway": null,
              "dns": null,
              "mdp": null,
              "position_ordre": 0,
              "created_by": 4,
              "updated_by": null,
              "created_at": "2026-04-22T13:36:55.353Z",
              "updated_at": "2026-04-22T13:36:55.353Z"
            },
            {
              "id": 203,
              "salle_id": 58,
              "type_equipement": "TV",
              "reference": "SAMSUNG LH43QMCEPGCXEN",
              "serial_number": null,
              "description": "LH43QMCEPGCXEN",
              "sur_reseau": false,
              "ip": null,
              "masque": null,
              "gateway": null,
              "dns": null,
              "mdp": null,
              "position_ordre": 0,
              "created_by": 4,
              "updated_by": null,
              "created_at": "2026-04-22T13:36:55.354Z",
              "updated_at": "2026-04-22T13:36:55.354Z"
            }
          ]
        },
        {
          "id": 57,
          "chantier_id": 7,
          "nom": "OFFICE",
          "etage": null,
          "statut": "a_faire",
          "commentaire": null,
          "photo_url": null,
          "net_masque": "255.255.255.0",
          "net_gateway": null,
          "net_dns": null,
          "position_ordre": 0,
          "created_at": "2026-04-22T13:36:55.312Z",
          "updated_at": "2026-04-22T13:36:55.312Z",
          "produits": [
            {
              "id": 181,
              "salle_id": 57,
              "type_equipement": "TV",
              "reference": "Samsung Pied",
              "serial_number": null,
              "description": "Pied",
              "sur_reseau": false,
              "ip": null,
              "masque": null,
              "gateway": null,
              "dns": null,
              "mdp": null,
              "position_ordre": 0,
              "created_by": 4,
              "updated_by": null,
              "created_at": "2026-04-22T13:36:55.318Z",
              "updated_at": "2026-04-22T13:36:55.318Z"
            },
            {
              "id": 182,
              "salle_id": 57,
              "type_equipement": "TV",
              "reference": "Samsung LH55WMBWBGCXEN",
              "serial_number": null,
              "description": "LH55WMBWBGCXEN",
              "sur_reseau": false,
              "ip": null,
              "masque": null,
              "gateway": null,
              "dns": null,
              "mdp": null,
              "position_ordre": 0,
              "created_by": 4,
              "updated_by": null,
              "created_at": "2026-04-22T13:36:55.320Z",
              "updated_at": "2026-04-22T13:36:55.320Z"
            },
            {
              "id": 183,
              "salle_id": 57,
              "type_equipement": "Autre",
              "reference": "Screen'Up SCRMF3255",
              "serial_number": null,
              "description": "SCRMF3255",
              "sur_reseau": false,
              "ip": null,
              "masque": null,
              "gateway": null,
              "dns": null,
              "mdp": null,
              "position_ordre": 0,
              "created_by": 4,
              "updated_by": null,
              "created_at": "2026-04-22T13:36:55.322Z",
              "updated_at": "2026-04-22T13:36:55.322Z"
            },
            {
              "id": 184,
              "salle_id": 57,
              "type_equipement": "Autre",
              "reference": "Screen'Up SCRMF3255",
              "serial_number": null,
              "description": "SCRMF3255",
              "sur_reseau": false,
              "ip": null,
              "masque": null,
              "gateway": null,
              "dns": null,
              "mdp": null,
              "position_ordre": 0,
              "created_by": 4,
              "updated_by": null,
              "created_at": "2026-04-22T13:36:55.323Z",
              "updated_at": "2026-04-22T13:36:55.323Z"
            },
            {
              "id": 185,
              "salle_id": 57,
              "type_equipement": "TV",
              "reference": "SAMSUNG LH43QMCEPGCXEN",
              "serial_number": null,
              "description": "LH43QMCEPGCXEN",
              "sur_reseau": false,
              "ip": null,
              "masque": null,
              "gateway": null,
              "dns": null,
              "mdp": null,
              "position_ordre": 0,
              "created_by": 4,
              "updated_by": null,
              "created_at": "2026-04-22T13:36:55.325Z",
              "updated_at": "2026-04-22T13:36:55.325Z"
            },
            {
              "id": 186,
              "salle_id": 57,
              "type_equipement": "TV",
              "reference": "SAMSUNG LH43QMCEPGCXEN",
              "serial_number": null,
              "description": "LH43QMCEPGCXEN",
              "sur_reseau": false,
              "ip": null,
              "masque": null,
              "gateway": null,
              "dns": null,
              "mdp": null,
              "position_ordre": 0,
              "created_by": 4,
              "updated_by": null,
              "created_at": "2026-04-22T13:36:55.326Z",
              "updated_at": "2026-04-22T13:36:55.326Z"
            },
            {
              "id": 187,
              "salle_id": 57,
              "type_equipement": "Visio",
              "reference": "Poly Poly Studio X52",
              "serial_number": null,
              "description": "Poly Studio X52",
              "sur_reseau": false,
              "ip": null,
              "masque": null,
              "gateway": null,
              "dns": null,
              "mdp": null,
              "position_ordre": 0,
              "created_by": 4,
              "updated_by": null,
              "created_at": "2026-04-22T13:36:55.329Z",
              "updated_at": "2026-04-22T13:36:55.329Z"
            },
            {
              "id": 188,
              "salle_id": 57,
              "type_equipement": "Visio",
              "reference": "HP / POLY Poly Studio",
              "serial_number": null,
              "description": "Poly Studio",
              "sur_reseau": false,
              "ip": null,
              "masque": null,
              "gateway": null,
              "dns": null,
              "mdp": null,
              "position_ordre": 0,
              "created_by": 4,
              "updated_by": null,
              "created_at": "2026-04-22T13:36:55.330Z",
              "updated_at": "2026-04-22T13:36:55.330Z"
            },
            {
              "id": 189,
              "salle_id": 57,
              "type_equipement": "Visio",
              "reference": "Poly 2200-37860-001 //",
              "serial_number": null,
              "description": "2200-37860-001 //",
              "sur_reseau": false,
              "ip": null,
              "masque": null,
              "gateway": null,
              "dns": null,
              "mdp": null,
              "position_ordre": 0,
              "created_by": 4,
              "updated_by": null,
              "created_at": "2026-04-22T13:36:55.333Z",
              "updated_at": "2026-04-22T13:36:55.333Z"
            },
            {
              "id": 190,
              "salle_id": 57,
              "type_equipement": "Autre",
              "reference": "SCREEN'UP MF55100",
              "serial_number": null,
              "description": "MF55100",
              "sur_reseau": false,
              "ip": null,
              "masque": null,
              "gateway": null,
              "dns": null,
              "mdp": null,
              "position_ordre": 0,
              "created_by": 4,
              "updated_by": null,
              "created_at": "2026-04-22T13:36:55.334Z",
              "updated_at": "2026-04-22T13:36:55.334Z"
            },
            {
              "id": 191,
              "salle_id": 57,
              "type_equipement": "TV",
              "reference": "SAMSUNG LH75QMCEBGCXEN",
              "serial_number": null,
              "description": "LH75QMCEBGCXEN",
              "sur_reseau": false,
              "ip": null,
              "masque": null,
              "gateway": null,
              "dns": null,
              "mdp": null,
              "position_ordre": 0,
              "created_by": 4,
              "updated_by": null,
              "created_at": "2026-04-22T13:36:55.336Z",
              "updated_at": "2026-04-22T13:36:55.336Z"
            }
          ]
        },
        {
          "id": 59,
          "chantier_id": 7,
          "nom": "PROCESS CONTROL ROOM",
          "etage": null,
          "statut": "a_faire",
          "commentaire": null,
          "photo_url": null,
          "net_masque": "255.255.255.0",
          "net_gateway": null,
          "net_dns": null,
          "position_ordre": 0,
          "created_at": "2026-04-22T13:36:55.316Z",
          "updated_at": "2026-04-22T13:36:55.316Z",
          "produits": [
            {
              "id": 204,
              "salle_id": 59,
              "type_equipement": "Controleur",
              "reference": "Crestron TSW-TSW-770-MSMK-B-S",
              "serial_number": null,
              "description": "TSW-TSW-770-MSMK-B-S",
              "sur_reseau": false,
              "ip": null,
              "masque": null,
              "gateway": null,
              "dns": null,
              "mdp": null,
              "position_ordre": 0,
              "created_by": 4,
              "updated_by": null,
              "created_at": "2026-04-22T13:36:55.356Z",
              "updated_at": "2026-04-22T13:36:55.356Z"
            },
            {
              "id": 205,
              "salle_id": 59,
              "type_equipement": "Controleur",
              "reference": "Crestron TSS- TSS-770-B-S-LB KIT",
              "serial_number": null,
              "description": "TSS- TSS-770-B-S-LB KIT",
              "sur_reseau": false,
              "ip": null,
              "masque": null,
              "gateway": null,
              "dns": null,
              "mdp": null,
              "position_ordre": 0,
              "created_by": 4,
              "updated_by": null,
              "created_at": "2026-04-22T13:36:55.357Z",
              "updated_at": "2026-04-22T13:36:55.357Z"
            },
            {
              "id": 206,
              "salle_id": 59,
              "type_equipement": "Autre",
              "reference": "Poly Micro d'extension",
              "serial_number": null,
              "description": "Micro d'extension",
              "sur_reseau": false,
              "ip": null,
              "masque": null,
              "gateway": null,
              "dns": null,
              "mdp": null,
              "position_ordre": 0,
              "created_by": 4,
              "updated_by": null,
              "created_at": "2026-04-22T13:36:55.359Z",
              "updated_at": "2026-04-22T13:36:55.359Z"
            },
            {
              "id": 207,
              "salle_id": 59,
              "type_equipement": "Autre",
              "reference": "Screen'Up SCRMF3255",
              "serial_number": null,
              "description": "SCRMF3255",
              "sur_reseau": false,
              "ip": null,
              "masque": null,
              "gateway": null,
              "dns": null,
              "mdp": null,
              "position_ordre": 0,
              "created_by": 4,
              "updated_by": null,
              "created_at": "2026-04-22T13:36:55.360Z",
              "updated_at": "2026-04-22T13:36:55.360Z"
            },
            {
              "id": 208,
              "salle_id": 59,
              "type_equipement": "Autre",
              "reference": "Screen'Up SCRMF3255",
              "serial_number": null,
              "description": "SCRMF3255",
              "sur_reseau": false,
              "ip": null,
              "masque": null,
              "gateway": null,
              "dns": null,
              "mdp": null,
              "position_ordre": 0,
              "created_by": 4,
              "updated_by": null,
              "created_at": "2026-04-22T13:36:55.362Z",
              "updated_at": "2026-04-22T13:36:55.362Z"
            },
            {
              "id": 209,
              "salle_id": 59,
              "type_equipement": "TV",
              "reference": "SAMSUNG LH43QMCEPGCXEN",
              "serial_number": null,
              "description": "LH43QMCEPGCXEN",
              "sur_reseau": false,
              "ip": null,
              "masque": null,
              "gateway": null,
              "dns": null,
              "mdp": null,
              "position_ordre": 0,
              "created_by": 4,
              "updated_by": null,
              "created_at": "2026-04-22T13:36:55.363Z",
              "updated_at": "2026-04-22T13:36:55.363Z"
            },
            {
              "id": 210,
              "salle_id": 59,
              "type_equipement": "TV",
              "reference": "SAMSUNG LH43QMCEPGCXEN",
              "serial_number": null,
              "description": "LH43QMCEPGCXEN",
              "sur_reseau": false,
              "ip": null,
              "masque": null,
              "gateway": null,
              "dns": null,
              "mdp": null,
              "position_ordre": 0,
              "created_by": 4,
              "updated_by": null,
              "created_at": "2026-04-22T13:36:55.364Z",
              "updated_at": "2026-04-22T13:36:55.364Z"
            },
            {
              "id": 211,
              "salle_id": 59,
              "type_equipement": "Visio",
              "reference": "VISION VFM-",
              "serial_number": null,
              "description": "VFM-",
              "sur_reseau": false,
              "ip": null,
              "masque": null,
              "gateway": null,
              "dns": null,
              "mdp": null,
              "position_ordre": 0,
              "created_by": 4,
              "updated_by": null,
              "created_at": "2026-04-22T13:36:55.365Z",
              "updated_at": "2026-04-22T13:36:55.365Z"
            },
            {
              "id": 212,
              "salle_id": 59,
              "type_equipement": "Visio",
              "reference": "VISION VFM-",
              "serial_number": null,
              "description": "VFM-",
              "sur_reseau": false,
              "ip": null,
              "masque": null,
              "gateway": null,
              "dns": null,
              "mdp": null,
              "position_ordre": 0,
              "created_by": 4,
              "updated_by": null,
              "created_at": "2026-04-22T13:36:55.367Z",
              "updated_at": "2026-04-22T13:36:55.367Z"
            },
            {
              "id": 213,
              "salle_id": 59,
              "type_equipement": "Visio",
              "reference": "VISION VFM-",
              "serial_number": null,
              "description": "VFM-",
              "sur_reseau": false,
              "ip": null,
              "masque": null,
              "gateway": null,
              "dns": null,
              "mdp": null,
              "position_ordre": 0,
              "created_by": 4,
              "updated_by": null,
              "created_at": "2026-04-22T13:36:55.368Z",
              "updated_at": "2026-04-22T13:36:55.368Z"
            },
            {
              "id": 214,
              "salle_id": 59,
              "type_equipement": "Visio",
              "reference": "VISION VFM-",
              "serial_number": null,
              "description": "VFM-",
              "sur_reseau": false,
              "ip": null,
              "masque": null,
              "gateway": null,
              "dns": null,
              "mdp": null,
              "position_ordre": 0,
              "created_by": 4,
              "updated_by": null,
              "created_at": "2026-04-22T13:36:55.370Z",
              "updated_at": "2026-04-22T13:36:55.370Z"
            }
          ]
        }
      ]
    },
    {
      "id": 18,
      "nom": "UNIVERSITE DE LILLE",
      "client": "Agora",
      "adresse": "42 rue Paul Duez 59000 LILLE France",
      "date_debut": "2026-05-17T22:00:00.000Z",
      "date_fin": "2026-05-21T22:00:00.000Z",
      "statut": "a_faire",
      "description": "Importe depuis BDC PDF",
      "created_by": 4,
      "created_at": "2026-04-23T13:55:52.292Z",
      "updated_at": "2026-04-23T19:47:12.694Z",
      "salles": [
        {
          "id": 74,
          "chantier_id": 18,
          "nom": "MOUNT",
          "etage": null,
          "statut": "a_faire",
          "commentaire": null,
          "photo_url": "/uploads/salle_74_1776954964113.jpg",
          "net_masque": "255.255.255.0",
          "net_gateway": null,
          "net_dns": null,
          "position_ordre": 0,
          "created_at": "2026-04-23T13:55:52.296Z",
          "updated_at": "2026-04-27T08:58:21.254Z",
          "produits": [
            {
              "id": 541,
              "salle_id": 74,
              "type_equipement": "TV",
              "reference": "SONY FW-43BZ30L/TM",
              "serial_number": null,
              "description": "FW-43BZ30L/TM",
              "sur_reseau": false,
              "ip": null,
              "masque": null,
              "gateway": null,
              "dns": null,
              "mdp": null,
              "position_ordre": 0,
              "created_by": 4,
              "updated_by": null,
              "created_at": "2026-04-23T13:55:52.297Z",
              "updated_at": "2026-04-23T13:55:52.297Z"
            },
            {
              "id": 542,
              "salle_id": 74,
              "type_equipement": "TV",
              "reference": "SONY FW-43BZ30L/TM",
              "serial_number": null,
              "description": "FW-43BZ30L/TM",
              "sur_reseau": false,
              "ip": null,
              "masque": null,
              "gateway": null,
              "dns": null,
              "mdp": null,
              "position_ordre": 0,
              "created_by": 4,
              "updated_by": null,
              "created_at": "2026-04-23T13:55:52.300Z",
              "updated_at": "2026-04-23T13:55:52.300Z"
            },
            {
              "id": 543,
              "salle_id": 74,
              "type_equipement": "TV",
              "reference": "SONY FW-43BZ30L/TM",
              "serial_number": null,
              "description": "FW-43BZ30L/TM",
              "sur_reseau": false,
              "ip": null,
              "masque": null,
              "gateway": null,
              "dns": null,
              "mdp": null,
              "position_ordre": 0,
              "created_by": 4,
              "updated_by": null,
              "created_at": "2026-04-23T13:55:52.301Z",
              "updated_at": "2026-04-23T13:55:52.301Z"
            },
            {
              "id": 544,
              "salle_id": 74,
              "type_equipement": "TV",
              "reference": "SONY FW-43BZ30L/TM",
              "serial_number": null,
              "description": "FW-43BZ30L/TM",
              "sur_reseau": false,
              "ip": null,
              "masque": null,
              "gateway": null,
              "dns": null,
              "mdp": null,
              "position_ordre": 0,
              "created_by": 4,
              "updated_by": null,
              "created_at": "2026-04-23T13:55:52.302Z",
              "updated_at": "2026-04-23T13:55:52.302Z"
            },
            {
              "id": 545,
              "salle_id": 74,
              "type_equipement": "TV",
              "reference": "SONY FW-43BZ30L/TM",
              "serial_number": null,
              "description": "FW-43BZ30L/TM",
              "sur_reseau": false,
              "ip": null,
              "masque": null,
              "gateway": null,
              "dns": null,
              "mdp": null,
              "position_ordre": 0,
              "created_by": 4,
              "updated_by": null,
              "created_at": "2026-04-23T13:55:52.303Z",
              "updated_at": "2026-04-23T13:55:52.303Z"
            },
            {
              "id": 546,
              "salle_id": 74,
              "type_equipement": "TV",
              "reference": "SONY FW-43BZ30L/TM",
              "serial_number": null,
              "description": "FW-43BZ30L/TM",
              "sur_reseau": false,
              "ip": null,
              "masque": null,
              "gateway": null,
              "dns": null,
              "mdp": null,
              "position_ordre": 0,
              "created_by": 4,
              "updated_by": null,
              "created_at": "2026-04-23T13:55:52.305Z",
              "updated_at": "2026-04-23T13:55:52.305Z"
            },
            {
              "id": 547,
              "salle_id": 74,
              "type_equipement": "TV",
              "reference": "SONY FW-43BZ30L/TM",
              "serial_number": null,
              "description": "FW-43BZ30L/TM",
              "sur_reseau": false,
              "ip": null,
              "masque": null,
              "gateway": null,
              "dns": null,
              "mdp": null,
              "position_ordre": 0,
              "created_by": 4,
              "updated_by": null,
              "created_at": "2026-04-23T13:55:52.306Z",
              "updated_at": "2026-04-23T13:55:52.306Z"
            },
            {
              "id": 548,
              "salle_id": 74,
              "type_equipement": "TV",
              "reference": "SONY FW-43BZ30L/TM",
              "serial_number": null,
              "description": "FW-43BZ30L/TM",
              "sur_reseau": false,
              "ip": null,
              "masque": null,
              "gateway": null,
              "dns": null,
              "mdp": null,
              "position_ordre": 0,
              "created_by": 4,
              "updated_by": null,
              "created_at": "2026-04-23T13:55:52.308Z",
              "updated_at": "2026-04-23T13:55:52.308Z"
            },
            {
              "id": 549,
              "salle_id": 74,
              "type_equipement": "Visio",
              "reference": "JABRA PANACAST 50",
              "serial_number": null,
              "description": "PANACAST 50",
              "sur_reseau": false,
              "ip": null,
              "masque": null,
              "gateway": null,
              "dns": null,
              "mdp": null,
              "position_ordre": 0,
              "created_by": 4,
              "updated_by": null,
              "created_at": "2026-04-23T13:55:52.309Z",
              "updated_at": "2026-04-23T13:55:52.309Z"
            },
            {
              "id": 550,
              "salle_id": 74,
              "type_equipement": "Visio",
              "reference": "JABRA PANACAST 50",
              "serial_number": null,
              "description": "PANACAST 50",
              "sur_reseau": false,
              "ip": null,
              "masque": null,
              "gateway": null,
              "dns": null,
              "mdp": null,
              "position_ordre": 0,
              "created_by": 4,
              "updated_by": null,
              "created_at": "2026-04-23T13:55:52.311Z",
              "updated_at": "2026-04-23T13:55:52.311Z"
            },
            {
              "id": 551,
              "salle_id": 74,
              "type_equipement": "Visio",
              "reference": "JABRA PANACAST 50",
              "serial_number": null,
              "description": "PANACAST 50",
              "sur_reseau": false,
              "ip": null,
              "masque": null,
              "gateway": null,
              "dns": null,
              "mdp": null,
              "position_ordre": 0,
              "created_by": 4,
              "updated_by": null,
              "created_at": "2026-04-23T13:55:52.312Z",
              "updated_at": "2026-04-23T13:55:52.312Z"
            },
            {
              "id": 552,
              "salle_id": 74,
              "type_equipement": "Visio",
              "reference": "JABRA PANACAST 50",
              "serial_number": null,
              "description": "PANACAST 50",
              "sur_reseau": false,
              "ip": null,
              "masque": null,
              "gateway": null,
              "dns": null,
              "mdp": null,
              "position_ordre": 0,
              "created_by": 4,
              "updated_by": null,
              "created_at": "2026-04-23T13:55:52.314Z",
              "updated_at": "2026-04-23T13:55:52.314Z"
            },
            {
              "id": 553,
              "salle_id": 74,
              "type_equipement": "Visio",
              "reference": "JABRA PANACAST 50",
              "serial_number": null,
              "description": "PANACAST 50",
              "sur_reseau": false,
              "ip": null,
              "masque": null,
              "gateway": null,
              "dns": null,
              "mdp": null,
              "position_ordre": 0,
              "created_by": 4,
              "updated_by": null,
              "created_at": "2026-04-23T13:55:52.315Z",
              "updated_at": "2026-04-23T13:55:52.315Z"
            },
            {
              "id": 554,
              "salle_id": 74,
              "type_equipement": "Autre",
              "reference": "SPEECHI ST-86-UHD-",
              "serial_number": null,
              "description": "ST-86-UHD-",
              "sur_reseau": false,
              "ip": null,
              "masque": null,
              "gateway": null,
              "dns": null,
              "mdp": null,
              "position_ordre": 0,
              "created_by": 4,
              "updated_by": null,
              "created_at": "2026-04-23T13:55:52.317Z",
              "updated_at": "2026-04-23T13:55:52.317Z"
            },
            {
              "id": 555,
              "salle_id": 74,
              "type_equipement": "Autre",
              "reference": "SPEECHI ST-86-UHD-",
              "serial_number": null,
              "description": "ST-86-UHD-",
              "sur_reseau": false,
              "ip": null,
              "masque": null,
              "gateway": null,
              "dns": null,
              "mdp": null,
              "position_ordre": 0,
              "created_by": 4,
              "updated_by": null,
              "created_at": "2026-04-23T13:55:52.318Z",
              "updated_at": "2026-04-23T13:55:52.318Z"
            },
            {
              "id": 556,
              "salle_id": 74,
              "type_equipement": "Autre",
              "reference": "SPEECHI ST-86-UHD-",
              "serial_number": null,
              "description": "ST-86-UHD-",
              "sur_reseau": false,
              "ip": null,
              "masque": null,
              "gateway": null,
              "dns": null,
              "mdp": null,
              "position_ordre": 0,
              "created_by": 4,
              "updated_by": null,
              "created_at": "2026-04-23T13:55:52.319Z",
              "updated_at": "2026-04-23T13:55:52.319Z"
            },
            {
              "id": 557,
              "salle_id": 74,
              "type_equipement": "Videoprojecteur",
              "reference": "EPSON EB-760W",
              "serial_number": null,
              "description": "EB-760W",
              "sur_reseau": false,
              "ip": null,
              "masque": null,
              "gateway": null,
              "dns": null,
              "mdp": null,
              "position_ordre": 0,
              "created_by": 4,
              "updated_by": null,
              "created_at": "2026-04-23T13:55:52.320Z",
              "updated_at": "2026-04-23T13:55:52.320Z"
            },
            {
              "id": 558,
              "salle_id": 74,
              "type_equipement": "Videoprojecteur",
              "reference": "EPSON EB-760W",
              "serial_number": null,
              "description": "EB-760W",
              "sur_reseau": false,
              "ip": null,
              "masque": null,
              "gateway": null,
              "dns": null,
              "mdp": null,
              "position_ordre": 0,
              "created_by": 4,
              "updated_by": null,
              "created_at": "2026-04-23T13:55:52.322Z",
              "updated_at": "2026-04-23T13:55:52.322Z"
            },
            {
              "id": 559,
              "salle_id": 74,
              "type_equipement": "Videoprojecteur",
              "reference": "EPSON EB-760W",
              "serial_number": null,
              "description": "EB-760W",
              "sur_reseau": false,
              "ip": null,
              "masque": null,
              "gateway": null,
              "dns": null,
              "mdp": null,
              "position_ordre": 0,
              "created_by": 4,
              "updated_by": null,
              "created_at": "2026-04-23T13:55:52.323Z",
              "updated_at": "2026-04-23T13:55:52.323Z"
            },
            {
              "id": 560,
              "salle_id": 74,
              "type_equipement": "Videoprojecteur",
              "reference": "EPSON EB-760W",
              "serial_number": null,
              "description": "EB-760W",
              "sur_reseau": false,
              "ip": null,
              "masque": null,
              "gateway": null,
              "dns": null,
              "mdp": null,
              "position_ordre": 0,
              "created_by": 4,
              "updated_by": null,
              "created_at": "2026-04-23T13:55:52.325Z",
              "updated_at": "2026-04-23T13:55:52.325Z"
            },
            {
              "id": 561,
              "salle_id": 74,
              "type_equipement": "Controleur",
              "reference": "Extron Boitier de contrôle MLC 55 RS EU",
              "serial_number": "",
              "description": "Boitier de contrôle",
              "sur_reseau": false,
              "ip": "",
              "masque": "",
              "gateway": "",
              "dns": "",
              "mdp": "",
              "position_ordre": 0,
              "created_by": 4,
              "updated_by": 4,
              "created_at": "2026-04-23T13:55:52.329Z",
              "updated_at": "2026-04-23T13:56:26.662Z"
            },
            {
              "id": 565,
              "salle_id": 74,
              "type_equipement": "Autre",
              "reference": "[ST-OPS-i7-VPC-G12-PACK] [SPEECHI] PC Windows 11 ",
              "serial_number": null,
              "description": "",
              "sur_reseau": false,
              "ip": null,
              "masque": null,
              "gateway": null,
              "dns": null,
              "mdp": null,
              "position_ordre": 0,
              "created_by": 4,
              "updated_by": null,
              "created_at": "2026-04-23T13:55:52.335Z",
              "updated_at": "2026-04-23T13:55:52.335Z"
            },
            {
              "id": 567,
              "salle_id": 74,
              "type_equipement": "Autre",
              "reference": "[ST-OPS-i7-VPC-G12-PACK] [SPEECHI] PC Windows 11 ",
              "serial_number": null,
              "description": "",
              "sur_reseau": false,
              "ip": null,
              "masque": null,
              "gateway": null,
              "dns": null,
              "mdp": null,
              "position_ordre": 0,
              "created_by": 4,
              "updated_by": null,
              "created_at": "2026-04-23T13:55:52.338Z",
              "updated_at": "2026-04-23T13:55:52.338Z"
            },
            {
              "id": 568,
              "salle_id": 74,
              "type_equipement": "Visio",
              "reference": "[UC CAM120ULB-1] [IIYAMA] UC CAM120ULB-1",
              "serial_number": null,
              "description": "",
              "sur_reseau": false,
              "ip": null,
              "masque": null,
              "gateway": null,
              "dns": null,
              "mdp": null,
              "position_ordre": 0,
              "created_by": 4,
              "updated_by": null,
              "created_at": "2026-04-23T13:55:52.339Z",
              "updated_at": "2026-04-23T13:55:52.339Z"
            },
            {
              "id": 569,
              "salle_id": 74,
              "type_equipement": "Visio",
              "reference": "[UC CAM120ULB-1] [IIYAMA] UC CAM120ULB-1",
              "serial_number": null,
              "description": "",
              "sur_reseau": false,
              "ip": null,
              "masque": null,
              "gateway": null,
              "dns": null,
              "mdp": null,
              "position_ordre": 0,
              "created_by": 4,
              "updated_by": null,
              "created_at": "2026-04-23T13:55:52.340Z",
              "updated_at": "2026-04-23T13:55:52.340Z"
            },
            {
              "id": 570,
              "salle_id": 74,
              "type_equipement": "Visio",
              "reference": "[UC CAM120ULB-1] [IIYAMA] UC CAM120ULB-1",
              "serial_number": null,
              "description": "",
              "sur_reseau": false,
              "ip": null,
              "masque": null,
              "gateway": null,
              "dns": null,
              "mdp": null,
              "position_ordre": 0,
              "created_by": 4,
              "updated_by": null,
              "created_at": "2026-04-23T13:55:52.342Z",
              "updated_at": "2026-04-23T13:55:52.342Z"
            },
            {
              "id": 571,
              "salle_id": 74,
              "type_equipement": "Visio",
              "reference": "[UC CAM120ULB-1] [IIYAMA] UC CAM120ULB-1",
              "serial_number": null,
              "description": "",
              "sur_reseau": false,
              "ip": null,
              "masque": null,
              "gateway": null,
              "dns": null,
              "mdp": null,
              "position_ordre": 0,
              "created_by": 4,
              "updated_by": null,
              "created_at": "2026-04-23T13:55:52.344Z",
              "updated_at": "2026-04-23T13:55:52.344Z"
            },
            {
              "id": 572,
              "salle_id": 74,
              "type_equipement": "Visio",
              "reference": "[UC CAM120ULB-1] [IIYAMA] UC CAM120ULB-1",
              "serial_number": null,
              "description": "",
              "sur_reseau": false,
              "ip": null,
              "masque": null,
              "gateway": null,
              "dns": null,
              "mdp": null,
              "position_ordre": 0,
              "created_by": 4,
              "updated_by": null,
              "created_at": "2026-04-23T13:55:52.345Z",
              "updated_at": "2026-04-23T13:55:52.345Z"
            },
            {
              "id": 564,
              "salle_id": 74,
              "type_equipement": "Controleur",
              "reference": "Extron Boitier de contrôle MLC 55 RS EU",
              "serial_number": "",
              "description": "Boitier de contrôle",
              "sur_reseau": false,
              "ip": "",
              "masque": "",
              "gateway": "",
              "dns": "",
              "mdp": "",
              "position_ordre": 0,
              "created_by": 4,
              "updated_by": 4,
              "created_at": "2026-04-23T13:55:52.334Z",
              "updated_at": "2026-04-23T13:56:08.235Z"
            },
            {
              "id": 563,
              "salle_id": 74,
              "type_equipement": "Controleur",
              "reference": "Extron Boitier de contrôle MLC 55 RS EU",
              "serial_number": "",
              "description": "Boitier de contrôle",
              "sur_reseau": false,
              "ip": "",
              "masque": "",
              "gateway": "",
              "dns": "",
              "mdp": "",
              "position_ordre": 0,
              "created_by": 4,
              "updated_by": 4,
              "created_at": "2026-04-23T13:55:52.332Z",
              "updated_at": "2026-04-23T13:56:14.998Z"
            },
            {
              "id": 566,
              "salle_id": 74,
              "type_equipement": "Autre",
              "reference": "[ST-OPS-i7-VPC-G12-PACK] [SPEECHI] PC Windows 11 ",
              "serial_number": "",
              "description": "",
              "sur_reseau": false,
              "ip": "",
              "masque": "",
              "gateway": "",
              "dns": "",
              "mdp": "",
              "position_ordre": 0,
              "created_by": 4,
              "updated_by": 4,
              "created_at": "2026-04-23T13:55:52.337Z",
              "updated_at": "2026-04-23T13:56:37.422Z"
            },
            {
              "id": 562,
              "salle_id": 74,
              "type_equipement": "Controleur",
              "reference": "Extron Boitier de contrôle MLC 55 RS EU",
              "serial_number": "",
              "description": "Boitier de contrôle",
              "sur_reseau": false,
              "ip": "",
              "masque": "",
              "gateway": "",
              "dns": "",
              "mdp": "",
              "position_ordre": 0,
              "created_by": 4,
              "updated_by": 4,
              "created_at": "2026-04-23T13:55:52.331Z",
              "updated_at": "2026-04-23T13:56:20.138Z"
            }
          ]
        }
      ]
    },
    {
      "id": 19,
      "nom": "Hydac Amiens",
      "client": " +33 3 87 29 26 00",
      "adresse": "15 Avenue Du Great Eastern 80330 LONGUEAU",
      "date_debut": null,
      "date_fin": null,
      "statut": "en_cours",
      "description": "Importe depuis BDC PDF",
      "created_by": 6,
      "created_at": "2026-04-24T09:36:13.484Z",
      "updated_at": "2026-04-27T13:36:36.174Z",
      "salles": [
        {
          "id": 75,
          "chantier_id": 19,
          "nom": "Salle principale",
          "etage": null,
          "statut": "en_cours",
          "commentaire": null,
          "photo_url": null,
          "net_masque": "255.255.255.0",
          "net_gateway": null,
          "net_dns": null,
          "position_ordre": 0,
          "created_at": "2026-04-24T09:36:13.509Z",
          "updated_at": "2026-04-27T12:28:40.546Z",
          "produits": [
            {
              "id": 573,
              "salle_id": 75,
              "type_equipement": "Visio",
              "reference": "BARCO CX-20",
              "serial_number": null,
              "description": "Systeme de",
              "sur_reseau": false,
              "ip": null,
              "masque": null,
              "gateway": null,
              "dns": null,
              "mdp": null,
              "position_ordre": 0,
              "created_by": 6,
              "updated_by": null,
              "created_at": "2026-04-24T09:36:13.511Z",
              "updated_at": "2026-04-24T09:36:13.511Z"
            },
            {
              "id": 574,
              "salle_id": 75,
              "type_equipement": "Visio",
              "reference": "LOGITECH Rally Bar",
              "serial_number": null,
              "description": "Rally Bar",
              "sur_reseau": false,
              "ip": null,
              "masque": null,
              "gateway": null,
              "dns": null,
              "mdp": null,
              "position_ordre": 0,
              "created_by": 6,
              "updated_by": null,
              "created_at": "2026-04-24T09:36:13.516Z",
              "updated_at": "2026-04-24T09:36:13.516Z"
            },
            {
              "id": 575,
              "salle_id": 75,
              "type_equipement": "TV",
              "reference": "SAMSUNG LH75QMCEBGCXEN",
              "serial_number": null,
              "description": "LH75QMCEBGCXEN",
              "sur_reseau": false,
              "ip": null,
              "masque": null,
              "gateway": null,
              "dns": null,
              "mdp": null,
              "position_ordre": 0,
              "created_by": 6,
              "updated_by": null,
              "created_at": "2026-04-24T09:36:13.518Z",
              "updated_at": "2026-04-24T09:36:13.518Z"
            }
          ]
        }
      ]
    },
    {
      "id": 21,
      "nom": "AV-Speak",
      "client": "Sonoco",
      "adresse": "rue François Jacob 62800 Lièvin France",
      "date_debut": null,
      "date_fin": null,
      "statut": "en_cours",
      "description": "Importe depuis BDC PDF",
      "created_by": 4,
      "created_at": "2026-04-27T13:36:07.937Z",
      "updated_at": "2026-04-27T13:37:03.158Z",
      "salles": [
        {
          "id": 78,
          "chantier_id": 21,
          "nom": "Accueil ",
          "etage": "",
          "statut": "a_faire",
          "commentaire": null,
          "photo_url": null,
          "net_masque": "255.255.255.0",
          "net_gateway": "",
          "net_dns": "",
          "position_ordre": 0,
          "created_at": "2026-04-27T13:36:07.940Z",
          "updated_at": "2026-04-27T15:04:45.545Z",
          "produits": [
            {
              "id": 582,
              "salle_id": 78,
              "type_equipement": "TV",
              "reference": "Beetronics Écran Tactile 12 Pouces en",
              "serial_number": null,
              "description": "Écran Tactile 12 Pouces en",
              "sur_reseau": false,
              "ip": null,
              "masque": null,
              "gateway": null,
              "dns": null,
              "mdp": null,
              "position_ordre": 0,
              "created_by": 4,
              "updated_by": null,
              "created_at": "2026-04-27T13:36:07.941Z",
              "updated_at": "2026-04-27T13:36:07.941Z"
            },
            {
              "id": 583,
              "salle_id": 78,
              "type_equipement": "Controleur",
              "reference": "mini PC Celeron N4000",
              "serial_number": null,
              "description": "",
              "sur_reseau": false,
              "ip": null,
              "masque": null,
              "gateway": null,
              "dns": null,
              "mdp": null,
              "position_ordre": 0,
              "created_by": 4,
              "updated_by": null,
              "created_at": "2026-04-27T13:36:07.944Z",
              "updated_at": "2026-04-27T13:36:07.944Z"
            }
          ]
        }
      ]
    }
  ]
}